CHANGELOG.txt
pymisp_async/__init__.py
pymisp_async/abstract.py
pymisp_async/api.py
pymisp_async/data/describeTypes.json
pymisp_async/data/schema-lax.json
pymisp_async/data/schema.json
pymisp_async/exceptions.py
pymisp_async/mispevent.py
pymisp_async/py.typed
pymisp_async/tools/__init__.py
pymisp_async/tools/_psl_faup.py
pymisp_async/tools/abstractgenerator.py
pymisp_async/tools/asnobject.py
pymisp_async/tools/create_misp_object.py
pymisp_async/tools/csvloader.py
pymisp_async/tools/domainipobject.py
pymisp_async/tools/elfobject.py
pymisp_async/tools/emailobject.py
pymisp_async/tools/ext_lookups.py
pymisp_async/tools/fail2banobject.py
pymisp_async/tools/feed.py
pymisp_async/tools/fileobject.py
pymisp_async/tools/genericgenerator.py
pymisp_async/tools/geolocationobject.py
pymisp_async/tools/git_vuln_finder_object.py
pymisp_async/tools/load_warninglists.py
pymisp_async/tools/machoobject.py
pymisp_async/tools/microblogobject.py
pymisp_async/tools/neo4j.py
pymisp_async/tools/openioc.py
pymisp_async/tools/peobject.py
pymisp_async/tools/reportlab_generator.py
pymisp_async/tools/sbsignatureobject.py
pymisp_async/tools/sshauthkeyobject.py
pymisp_async/tools/stix.py
pymisp_async/tools/update_objects.py
pymisp_async/tools/urlobject.py
pymisp_async/tools/vehicleobject.py
pymisp_async/tools/vtreportobject.py
pymisp_async-2.4.182.dist-info/LICENSE
pymisp_async-2.4.182.dist-info/METADATA
pymisp_async-2.4.182.dist-info/WHEEL
pymisp_async-2.4.182.dist-info/RECORD
