Metadata-Version: 2.1
Name: pymisp-async
Version: 2.4.182
Summary: Python async API for MISP.
Home-page: https://github.com/MISP/PyMISP
License: BSD-2-Clause
Author: Raphaël Vinot
Author-email: raphael.vinot@circl.lu
Requires-Python: >=3.8,<4.0
Classifier: Development Status :: 5 - Production/Stable
Classifier: Environment :: Console
Classifier: Intended Audience :: Information Technology
Classifier: Intended Audience :: Science/Research
Classifier: Intended Audience :: Telecommunications Industry
Classifier: License :: OSI Approved :: BSD License
Classifier: Operating System :: POSIX :: Linux
Classifier: Programming Language :: Python :: 3
Classifier: Programming Language :: Python :: 3.8
Classifier: Programming Language :: Python :: 3.9
Classifier: Programming Language :: Python :: 3.10
Classifier: Programming Language :: Python :: 3.11
Classifier: Programming Language :: Python :: 3.10
Classifier: Programming Language :: Python :: 3.11
Classifier: Programming Language :: Python :: 3.8
Classifier: Programming Language :: Python :: 3.9
Classifier: Topic :: Internet
Classifier: Topic :: Security
Provides-Extra: brotli
Provides-Extra: docs
Provides-Extra: email
Provides-Extra: fileobjects
Provides-Extra: openioc
Provides-Extra: pdfexport
Provides-Extra: url
Provides-Extra: virustotal
Requires-Dist: RTFDE (>=0.1.1,<0.2.0) ; extra == "email"
Requires-Dist: Sphinx (<7.2) ; (python_version < "3.9") and (extra == "docs")
Requires-Dist: Sphinx (>=7.2,<8.0) ; (python_version >= "3.9") and (extra == "docs")
Requires-Dist: aiohttp (>=3.9.1,<4.0.0)
Requires-Dist: asyncio (>=3.4.3,<4.0.0)
Requires-Dist: beautifulsoup4 (>=4.12.2,<5.0.0) ; extra == "openioc"
Requires-Dist: deprecated (>=1.2.14,<2.0.0)
Requires-Dist: extract_msg (>=0.47.0,<0.48.0) ; extra == "email"
Requires-Dist: jsonschema (>=4.20.0,<5.0.0)
Requires-Dist: lief (>=0.13.2,<0.14.0) ; extra == "fileobjects"
Requires-Dist: oletools (>=0.60.1,<0.61.0) ; extra == "email"
Requires-Dist: publicsuffixlist (>=0.10.0.20231214,<0.11.0.0)
Requires-Dist: pydeep2 (>=0.5.1,<0.6.0) ; extra == "fileobjects"
Requires-Dist: pyfaup (>=1.2,<2.0) ; extra == "url"
Requires-Dist: python-dateutil (>=2.8.2,<3.0.0)
Requires-Dist: python-magic (>=0.4.27,<0.5.0) ; extra == "fileobjects"
Requires-Dist: recommonmark (>=0.7.1,<0.8.0) ; extra == "docs"
Requires-Dist: reportlab (>=4.0.8,<5.0.0) ; extra == "pdfexport"
Requires-Dist: requests (>=2.31.0,<3.0.0)
Requires-Dist: sphinx-autodoc-typehints (>=1.25.2,<2.0.0) ; extra == "docs"
Requires-Dist: urllib3[brotli] ; extra == "brotli"
Requires-Dist: validators (>=0.22.0,<0.23.0) ; extra == "virustotal"
Project-URL: Bug Tracker, https://github.com/MISP/PyMISP/issues
Project-URL: Documentation, https://pymisp.readthedocs.io
Project-URL: Repository, https://github.com/MISP/PyMISP
Project-URL: Source, https://github.com/MISP/PyMISP
